hunterMakesPy/__init__.py
hunterMakesPy/_theSSOT.py
hunterMakesPy/coping.py
hunterMakesPy/dataStructures.py
hunterMakesPy/filesystemToolkit.py
hunterMakesPy/parseParameters.py
hunterMakesPy/py.typed
hunterMakesPy/pytestForYourUse.py
hunterMakesPy/theTypes.py
hunterMakesPy/tests/__init__.py
hunterMakesPy/tests/conftest.py
hunterMakesPy/tests/test_coping.py
hunterMakesPy/tests/test_dataStructures.py
hunterMakesPy/tests/test_filesystemToolkit.py
hunterMakesPy/tests/test_parseParameters.py
hunterMakesPy/tests/test_theTypes.py
huntermakespy-0.3.4.dist-info/licenses/LICENSE
huntermakespy-0.3.4.dist-info/METADATA
huntermakespy-0.3.4.dist-info/WHEEL
huntermakespy-0.3.4.dist-info/top_level.txt
huntermakespy-0.3.4.dist-info/RECORD
