Metadata-Version: 2.4
Name: hunterMakesPy
Version: 0.3.4
Summary: Easy Python functions making making functional Python functions easier.
Author-email: Hunter Hogan <HunterHogan@pm.me>
License: CC-BY-NC-4.0
Project-URL: Donate, https://www.patreon.com/integrated
Project-URL: Homepage, https://github.com/hunterhogan/hunterMakesPy
Project-URL: Issues, https://github.com/hunterhogan/hunterMakesPy/issues
Project-URL: Repository, https://github.com/hunterhogan/hunterMakesPy
Keywords: attribute loading,concurrency limit,configuration,defensive programming,dictionary merging,directory creation,dynamic import,error propagation,file system utilities,input validation,integer parsing,module loading,nested data structures,package settings,parameter validation,pytest,string extraction,test utilities
Classifier: Development Status :: 5 - Production/Stable
Classifier: Environment :: Console
Classifier: Framework :: Pytest
Classifier: Intended Audience :: Developers
Classifier: Intended Audience :: End Users/Desktop
Classifier: Intended Audience :: Other Audience
Classifier: Natural Language :: English
Classifier: Operating System :: OS Independent
Classifier: Programming Language :: Python
Classifier: Programming Language :: Python :: 3
Classifier: Programming Language :: Python :: 3.11
Classifier: Programming Language :: Python :: 3.12
Classifier: Programming Language :: Python :: 3.13
Classifier: Programming Language :: Python :: 3.14
Classifier: Programming Language :: Python :: Implementation :: CPython
Classifier: Topic :: Software Development :: Libraries :: Python Modules
Classifier: Topic :: Utilities
Classifier: Typing :: Typed
Requires-Python: >=3.11
License-File: LICENSE
Requires-Dist: autoflake
Requires-Dist: charset_normalizer
Requires-Dist: isort
Requires-Dist: more_itertools
Requires-Dist: numpy
Provides-Extra: development
Requires-Dist: setuptools-scm; extra == "development"
Provides-Extra: testing
Requires-Dist: pytest; extra == "testing"
Requires-Dist: pytest-cov; extra == "testing"
Requires-Dist: pytest-xdist; extra == "testing"
Dynamic: license-file
